inelsmqtt/__init__.py
inelsmqtt/config.py
inelsmqtt/const.py
inelsmqtt/discovery.py
inelsmqtt/mqtt_client.py
inelsmqtt/util.py
inelsmqtt/devices/__init__.py
inelsmqtt/devices/light.py
inelsmqtt/devices/sensor.py
inelsmqtt/devices/switch.py
inelsmqtt/devices/switch2.py
tests/__init__.py
tests/const.py
tests/discovery_test.py
tests/inels_mqtt_test.py
tests/online_test.py
tests/devices/__init__.py
tests/devices/device_test.py
tests/devices/rfdac_71b_test.py
tests/devices/rfsti_11b_test.py
tests/devices/setup_test.py
inels_mqtt-0.0.60.dist-info/LICENSE
inels_mqtt-0.0.60.dist-info/METADATA
inels_mqtt-0.0.60.dist-info/WHEEL
inels_mqtt-0.0.60.dist-info/top_level.txt
inels_mqtt-0.0.60.dist-info/RECORD
