Metadata-Version: 2.1
Name: inels-mqtt
Version: 0.0.60
Summary: Python library for iNels mqtt protocol
Home-page: https://github.com/Nejezchleb/inels-mqtt
Author: Elko EP s.r.o.
Author-email: nejezchleb@elkoep.cz
License: MIT
Keywords: iNels,Elko EP,Home assistant integration
Classifier: License :: OSI Approved :: MIT License
Classifier: Programming Language :: Python :: 3
Classifier: Programming Language :: Python :: 3.9
License-File: LICENSE
